jon/__init__.py
jon/cli.py
jon/datatypes.py
jon/main.py
jon/parsing.py
jon/stages.py
jon/tokens.py
jon/utils.py
jon/validation.py
pyjon-1.0.0.dist-info/METADATA
pyjon-1.0.0.dist-info/WHEEL
pyjon-1.0.0.dist-info/entry_points.txt
pyjon-1.0.0.dist-info/licenses/LICENSE
pyjon-1.0.0.dist-info/RECORD
