Metadata-Version: 2.1
Name: pyjon
Version: 1.0.0
Summary: A Python package to manipulate JON documents
Project-URL: repository, https://github.com/just1not2/pyjon.git
Project-URL: documentation, https://github.com/just1not2/pyjon/blob/main/README.md
Author-email: Justin Béra <me@just1not2.org>
License:                                  Apache License
License-File: LICENSE
Keywords: jon,parser,pyjon
Classifier: License :: OSI Approved :: Apache Software License
Classifier: Operating System :: OS Independent
Classifier: Programming Language :: Python :: 3
Requires-Python: >=3.7
